Metadata-Version: 2.4
Name: excolor
Version: 0.1.1
Summary: Extended colors for python
Home-page: https://github.com/timpyrkov/excolor
Author: Tim Pyrkov
Author-email: tim.pyrkov@gmail.com
License: MIT License
Classifier: Programming Language :: Python :: 3
Classifier: License :: OSI Approved :: MIT License
Classifier: Topic :: Artistic Software
Requires-Python: >=3.6
License-File: LICENSE
Requires-Dist: numpy
Requires-Dist: pandas
Requires-Dist: scipy
Requires-Dist: pillow
Requires-Dist: matplotlib
Requires-Dist: cycler
Requires-Dist: opencv-python
Requires-Dist: pythonperlin
Requires-Dist: requests
Dynamic: author
Dynamic: author-email
Dynamic: classifier
Dynamic: description
Dynamic: description-content-type
Dynamic: home-page
Dynamic: license
Dynamic: license-file
Dynamic: requires-dist
Dynamic: requires-python
Dynamic: summary
